json2args/__init__.py
json2args/__version__.py
json2args/data.py
json2args/exceptions.py
json2args/logger.py
json2args/parameter.py
json2args/typed.py
json2args/util.py
json2args-0.7.0.dist-info/LICENSE
json2args-0.7.0.dist-info/METADATA
json2args-0.7.0.dist-info/WHEEL
json2args-0.7.0.dist-info/top_level.txt
json2args-0.7.0.dist-info/RECORD
