Metadata-Version: 2.1
Name: json2args
Version: 0.7.0
Summary: Read keyword arguments from json file automagically
Author: Mirko Mälicke
Author-email: mirko@hydrocode.de
License: MIT
License-File: LICENSE
Requires-Dist: pyyaml
Requires-Dist: python-dateutil
Requires-Dist: typing-extensions
Requires-Dist: pydantic
Provides-Extra: data
Requires-Dist: numpy <2.0.0 ; extra == 'data'
Requires-Dist: pandas ; extra == 'data'
Requires-Dist: polars ; extra == 'data'
Requires-Dist: pyarrow ; extra == 'data'
Requires-Dist: xarray ; extra == 'data'
Requires-Dist: netCDF4 ; extra == 'data'
Requires-Dist: dask ; extra == 'data'
Provides-Extra: tests
Requires-Dist: pytest ; extra == 'tests'
Requires-Dist: pytest-cov ; extra == 'tests'
